{
  "title": "[속보]트럼프 대통령 “봉쇄선 접근 시 즉각 제거”…초강경 해상 경고에 긴장 고조",
  "tag": "오늘의 픽 · 정치",
  "emoji": "🏛️",
  "summary": [
    "[CBC뉴스] 도널드 트럼프 대통령이 이란을 ",
    "이어 “신속하고 잔혹한 방식이 될 것”이라며 ",
    ""
  ],
  "link": "https://www.cbci.co.kr/news/articleView.html?idxno=567592",
  "source": "cbci.co.kr",
  "score": 2.5,
  "date": "2026-04-13",
  "content": "[CBC뉴스] 도널드 트럼프 대통령이 이란을 겨냥한 해상 봉쇄 조치와 관련해 초강경 발언을 내놓으며 중동 지역 긴장이 한층 격화되고 있다.트럼프 대통령은 트루스소셜 최근 메시지를 통해 “봉쇄선에 접근하는 선박이 있을 경우, 밀매선을 단속할 때 사용하는 것과 동일한 살상 수단을 동원해 즉시 제거할 것”이라고 밝혔다. 이어 “신속하고 잔혹한 방식이 될 것”이라며 군사적 대응 의지를 분명히 했다.이번 발언은 미국이 이란 전 해안과 항구를 대상으로 해상 봉쇄를 공식화한 이후 나온 것으로, 실제 군사 행동 가능성을 명확히 시사한 것으로 해석",
  "reactions": {
    "junhyuk": "트럼프 대통령의 초강경 발언은 이란에 대한 군사적 대응 가능성을 높이며 중동 지역의 긴장을 더욱 심화시키고 있다.",
    "hana": "이번 뉴스는 정말 걱정되는 상황이에요. 여러분은 어떻게 생각하세요? 좋음 / 모르겠음 / 걱정됨"
  },
  "analysis": {
    "mainTopic": "미국의 이란 해상 봉쇄 조치로 중동 지역 긴장이 고조되고 있다.",
    "mainKeyword": "봉쇄",
    "mainMood": "긴장",
    "reason": "미국의 해상 봉쇄 조치는 이란과의 군사적 갈등을 심화시킨다. 이란의 반응에 따라 중동 지역의 불안정성이 더욱 커질 수 있다."
  }
}